rst_to_myst/__init__.py
rst_to_myst/cli.py
rst_to_myst/inliner.py
rst_to_myst/markdownit.py
rst_to_myst/mdformat_render.py
rst_to_myst/namespace.py
rst_to_myst/nodes.py
rst_to_myst/parser.py
rst_to_myst/states.py
rst_to_myst/utils.py
rst_to_myst/data/__init__.py
rst_to_myst/data/directives.yml
rst_to_myst-0.3.3.dist-info/entry_points.txt
rst_to_myst-0.3.3.dist-info/LICENSE
rst_to_myst-0.3.3.dist-info/WHEEL
rst_to_myst-0.3.3.dist-info/METADATA
rst_to_myst-0.3.3.dist-info/RECORD
