Metadata-Version: 2.1
Name: rst-to-myst
Version: 0.3.3
Summary: Convert RST to MyST-Markdown.
Home-page: https://github.com/executablebooks/rst-to-myst
Keywords: restructuredtext,markdown,myst
Author: Chris Sewell
Author-email: executablebooks@gmail.com
Requires-Python: >=3.7
Classifier: Intended Audience :: Developers
Classifier: License :: OSI Approved :: MIT License
Classifier: Programming Language :: Python :: 3
Classifier: Topic :: Software Development :: Libraries :: Python Modules
Requires-Dist: docutils>=0.15,<0.18
Requires-Dist: importlib_resources~=3.1;python_version<'3.9'
Requires-Dist: pyyaml
Requires-Dist: markdown-it-py~=1.0
Requires-Dist: mdformat~=0.7.6
Requires-Dist: mdformat-myst~=0.1.4
Requires-Dist: mdformat-deflist~=0.1.0
Requires-Dist: click>=7.1,<9
Requires-Dist: myst-parser ; extra == "docs"
Requires-Dist: sphinx-book-theme ; extra == "docs"
Requires-Dist: sphinx-click ; extra == "docs"
Requires-Dist: sphinx-design ; extra == "docs"
Requires-Dist: sphinx>=3.2,<5 ; extra == "sphinx"
Requires-Dist: pytest~=6.0 ; extra == "test"
Requires-Dist: coverage ; extra == "test"
Requires-Dist: pytest-cov ; extra == "test"
Requires-Dist: pytest-regressions ; extra == "test"
Provides-Extra: docs
Provides-Extra: sphinx
Provides-Extra: test
